odoo/addons/delivery_price_method/README.rst
odoo/addons/delivery_price_method/__init__.py
odoo/addons/delivery_price_method/__manifest__.py
odoo/addons/delivery_price_method/i18n/delivery_price_method.pot
odoo/addons/delivery_price_method/models/__init__.py
odoo/addons/delivery_price_method/models/delivery_carrier.py
odoo/addons/delivery_price_method/readme/CONTRIBUTORS.rst
odoo/addons/delivery_price_method/readme/DESCRIPTION.rst
odoo/addons/delivery_price_method/readme/USAGE.rst
odoo/addons/delivery_price_method/static/description/icon.png
odoo/addons/delivery_price_method/static/description/index.html
odoo/addons/delivery_price_method/tests/__init__.py
odoo/addons/delivery_price_method/tests/test_delivery_price_method.py
odoo/addons/delivery_price_method/views/delivery_carrier_views.xml
odoo13_addon_delivery_price_method-13.0.1.0.2.dist-info/METADATA
odoo13_addon_delivery_price_method-13.0.1.0.2.dist-info/WHEEL
odoo13_addon_delivery_price_method-13.0.1.0.2.dist-info/top_level.txt
odoo13_addon_delivery_price_method-13.0.1.0.2.dist-info/RECORD
